pyimagen/__init__.py
pyimagen/app.py
pyimagen-0.3.2.dist-info/METADATA
pyimagen-0.3.2.dist-info/WHEEL
pyimagen-0.3.2.dist-info/entry_points.txt
pyimagen-0.3.2.dist-info/licenses/LICENSE
pyimagen-0.3.2.dist-info/RECORD
