Metadata-Version: 2.3
Name: pyimagen
Version: 0.3.2
Summary: A PyQt6-based AI image generation desktop application
Project-URL: Homepage, https://github.com/ricklamers/pyimagen
Project-URL: Repository, https://github.com/ricklamers/pyimagen.git
Project-URL: Issues, https://github.com/ricklamers/pyimagen/issues
Author-email: Rick Lamers <ricklamers@gmail.com>
License: MIT License
Keywords: ai,desktop,gui,image generation,pyqt
Classifier: Development Status :: 3 - Alpha
Classifier: Intended Audience :: End Users/Desktop
Classifier: License :: OSI Approved :: MIT License
Classifier: Operating System :: OS Independent
Classifier: Programming Language :: Python :: 3
Classifier: Programming Language :: Python :: 3.8
Classifier: Programming Language :: Python :: 3.9
Classifier: Programming Language :: Python :: 3.10
Classifier: Programming Language :: Python :: 3.11
Classifier: Topic :: Desktop Environment
Classifier: Topic :: Multimedia :: Graphics
Requires-Python: >=3.8
Requires-Dist: fal-client<0.6.0,>=0.5.0
Requires-Dist: groq>=0.3.0
Requires-Dist: nest-asyncio>=1.5.0
Requires-Dist: numpy>=1.24.0
Requires-Dist: pillow>=10.0.0
Requires-Dist: pyqt6>=6.0.0
Requires-Dist: requests>=2.31.0
Provides-Extra: dev
Requires-Dist: build>=1.2.2; extra == 'dev'
Requires-Dist: twine>=4.0.0; extra == 'dev'
